curryproxy/__init__.py
curryproxy/errors.py
curryproxy/helpers.py
curryproxy/server.py
curryproxy/version.py
curryproxy/version.txt
curryproxy/wsgi.py
curryproxy/responses/__init__.py
curryproxy/responses/error_response.py
curryproxy/responses/metadata_response.py
curryproxy/responses/multiple_response.py
curryproxy/responses/response_base.py
curryproxy/responses/single_response.py
curryproxy/responses/status_response.py
curryproxy/routes/__init__.py
curryproxy/routes/config.py
curryproxy/routes/endpoints_route.py
curryproxy/routes/forwarding_route.py
curryproxy/routes/route_base.py
curryproxy/routes/status_route.py
curryproxy-2.1.1.dist-info/AUTHORS.md
curryproxy-2.1.1.dist-info/METADATA
curryproxy-2.1.1.dist-info/WHEEL
curryproxy-2.1.1.dist-info/top_level.txt
curryproxy-2.1.1.dist-info/RECORD
