Metadata-Version: 2.1
Name: curryproxy
Version: 2.1.1
Summary: A proxy and aggregator for querying multiple instances of an API spread across globally distributed data centers.
Home-page: https://github.com/rackerlabs/curryproxy
Author: Bryan Davidson
Author-email: bryan.davidson@rackspace.com
License: Apache 2.0
Platform: UNKNOWN
Classifier: Development Status :: 5 - Production/Stable
Classifier: License :: OSI Approved :: Apache Software License
Classifier: Natural Language :: English
Classifier: Operating System :: OS Independent
Classifier: Programming Language :: Python
Classifier: Programming Language :: Python :: 3
Classifier: Programming Language :: Python :: 3.6
Classifier: Topic :: Internet :: Proxy Servers
Classifier: Topic :: Internet :: WWW/HTTP :: WSGI :: Application
Classifier: Topic :: Software Development :: Libraries :: Python Modules
Requires-Python: >=3
Requires-Dist: grequests (<0.4,>=0.3)
Requires-Dist: pyyaml (<4,>=3.10)
Requires-Dist: requests (<2.8,>=2.2)
Requires-Dist: webob (<1.5,>=1.2)
Provides-Extra: frozen
Requires-Dist: WebOb (==1.4.2) ; extra == 'frozen'
Requires-Dist: gevent (==1.4.0) ; extra == 'frozen'
Requires-Dist: greenlet (==0.4.15) ; extra == 'frozen'
Requires-Dist: grequests (==0.3.0) ; extra == 'frozen'
Requires-Dist: pyyaml (==3.13) ; extra == 'frozen'
Requires-Dist: requests (==2.7.0) ; extra == 'frozen'
Provides-Extra: tests
Requires-Dist: mock ; extra == 'tests'
Requires-Dist: testtools ; extra == 'tests'
